slice_db/__init__.py
slice_db/common.py
slice_db/dump.py
slice_db/dump_memory.py
slice_db/dump_temp_table.py
slice_db/log.py
slice_db/restore.py
slice_db/schema.py
slice_db/slice.py
slice_db/sql.py
slice_db/transform.py
slice_db/version.py
slice_db/cli/__init__.py
slice_db/cli/common.py
slice_db/cli/dump.py
slice_db/cli/main.py
slice_db/cli/restore.py
slice_db/cli/schema.py
slice_db/cli/schema_filter.py
slice_db/cli/transform.py
slice_db/cli/transform_field.py
slice_db/collection/__init__.py
slice_db/collection/dict.py
slice_db/collection/set.py
slice_db/concurrent/__init__.py
slice_db/concurrent/graph.py
slice_db/concurrent/lock.py
slice_db/concurrent/queue.py
slice_db/data/__init__.py
slice_db/data/city.txt
slice_db/data/given-name.txt
slice_db/data/street.txt
slice_db/data/surname.txt
slice_db/data/us-state-abbr.txt
slice_db/data/us-state.txt
slice_db/data/word.txt
slice_db/data/zip.txt
slice_db/formats/__init__.py
slice_db/formats/dump.json
slice_db/formats/dump.py
slice_db/formats/manifest.json
slice_db/formats/manifest.py
slice_db/formats/transform.json
slice_db/formats/transform.py
slice_db/graph/__init__.py
slice_db/json/__init__.py
slice_db/pg/__init__.py
slice_db/pg/copy.py
slice_db/pg/token.py
slice_db/resource/__init__.py
slice_db/transforms/__init__.py
slice_db/transforms/address.py
slice_db/transforms/common.py
slice_db/transforms/date.py
slice_db/transforms/json.py
slice_db/transforms/person.py
slice_db/transforms/text.py
slice_db-5.1.16.dist-info/LICENSE.txt
slice_db-5.1.16.dist-info/METADATA
slice_db-5.1.16.dist-info/WHEEL
slice_db-5.1.16.dist-info/entry_points.txt
slice_db-5.1.16.dist-info/top_level.txt
slice_db-5.1.16.dist-info/RECORD
