Metadata-Version: 2.1
Name: slice-db
Version: 5.1.16
Summary: Capture, scrub, and restore subsets of PostgreSQL databases.
Home-page: https://github.com/rivethealth/slice-db
Author: Rivet Health
Author-email: ops@rivethealth.com
License: UNKNOWN
Project-URL: Issues, https://github.com/rivethealth/slice-db/issues
Platform: UNKNOWN
Classifier: License :: OSI Approved :: MIT License
Classifier: Operating System :: OS Independent
Classifier: Programming Language :: Python
Classifier: Programming Language :: Python :: 3
Requires-Python: >3.7.0
License-File: LICENSE.txt
Requires-Dist: asyncpg
Requires-Dist: dataclasses-json (==0.3.7)
Requires-Dist: jsonpath-ng
Requires-Dist: jsonschema
Requires-Dist: numpy
Requires-Dist: pg-sql
Requires-Dist: pyffx
Requires-Dist: uvloop
Provides-Extra: dev
Requires-Dist: black ; extra == 'dev'
Requires-Dist: isort ; extra == 'dev'
Requires-Dist: psutil ; extra == 'dev'
Requires-Dist: pytest ; extra == 'dev'
Requires-Dist: pytest-env ; extra == 'dev'
Requires-Dist: snapshottest ; extra == 'dev'
